song_metadata_embedder/__init__.py
song_metadata_embedder/classes/__init__.py
song_metadata_embedder/classes/embed_metadata_command.py
song_metadata_embedder/classes/embedders/__init__.py
song_metadata_embedder/classes/embedders/abstract_metadata_embedder.py
song_metadata_embedder/classes/embedders/flac_metadata_embedder.py
song_metadata_embedder/classes/embedders/m4a_metadata_embedder.py
song_metadata_embedder/classes/embedders/mp3_metadata_embedder.py
song_metadata_embedder/classes/embedders/ogg_metadata_embedder.py
song_metadata_embedder/classes/embedders/opus_metadata_embedder.py
song_metadata_embedder/classes/handlers/__init__.py
song_metadata_embedder/classes/handlers/abstract_metadata_handler.py
song_metadata_embedder/classes/handlers/flac_metadata_handler.py
song_metadata_embedder/classes/handlers/m4a_metadata_handler.py
song_metadata_embedder/classes/handlers/mp3_metadata_handler.py
song_metadata_embedder/classes/handlers/ogg_metadata_handler.py
song_metadata_embedder/classes/handlers/opus_metadata_handler.py
song_metadata_embedder/classes/song_metadata.py
song_metadata_embedder/classes/tag_preset.py
song_metadata_embedder/di/__init__.py
song_metadata_embedder/di/dependency_injector.py
song_metadata_embedder/errors/__init__.py
song_metadata_embedder/errors/song_metadata_error.py
song_metadata_embedder/errors/song_metadata_file_error.py
song_metadata_embedder/interfaces/__init__.py
song_metadata_embedder/interfaces/base_metadata_embedder.py
song_metadata_embedder/main.py
song_metadata_embedder/py.typed
song_metadata_embedder-0.0.1.dist-info/LICENSE
song_metadata_embedder-0.0.1.dist-info/METADATA
song_metadata_embedder-0.0.1.dist-info/WHEEL
song_metadata_embedder-0.0.1.dist-info/RECORD
